pyrilla/__init__.py
pyrilla/core.so
pyrilla/errors.py
pyrilla-0.0.2.dist-info/DESCRIPTION.rst
pyrilla-0.0.2.dist-info/METADATA
pyrilla-0.0.2.dist-info/RECORD
pyrilla-0.0.2.dist-info/WHEEL
pyrilla-0.0.2.dist-info/metadata.json
pyrilla-0.0.2.dist-info/top_level.txt
